_pyow/__init__.py
_pyow/exceptions.py
_pyow/pyow.py
_pyow/pyow_dupe.py
_pyow/types.py
_pyow/utils.py
_pyow/predicates/__init__.py
_pyow/predicates/base_predicate.py
_pyow/predicates/boolean.py
_pyow/predicates/dict.py
_pyow/predicates/error.py
_pyow/predicates/list.py
_pyow/predicates/number.py
_pyow/predicates/set.py
_pyow/predicates/string.py
pyow/__init__.py
pyow/exceptions.py
pyow/pyow.py
pyow/pyow_dupe.py
pyow/types.py
pyow/utils.py
pyow/decorators/__init__.py
pyow/operators/__init__.py
pyow/operators/nix.py
pyow/predicates/__init__.py
pyow/predicates/any.py
pyow/predicates/base_predicate.py
pyow/predicates/boolean.py
pyow/predicates/dict.py
pyow/predicates/error.py
pyow/predicates/list.py
pyow/predicates/number.py
pyow/predicates/set.py
pyow/predicates/string.py
pyow/predicates/tuple.py
pyow-0.0.4.dist-info/METADATA
pyow-0.0.4.dist-info/RECORD
pyow-0.0.4.dist-info/WHEEL
pyow-0.0.4.dist-info/top_level.txt
tests/__init__.py
tests/test_boolean_predicate.py
tests/test_decorator.py
tests/test_dict_predicate.py
tests/test_error_predicate.py
tests/test_list_predicate.py
tests/test_number_predicate.py
tests/test_pyow.py
tests/test_set_predicate.py
tests/test_string_predicate.py
tests/test_tuple_predicate.py
