Metadata-Version: 2.1
Name: pyow
Version: 0.0.4
Summary: A function argument validation for humans
Home-page: https://github.com/limelights/pyow
Author: Henrik Andersson
Author-email: henrik@http418.se
License: UNKNOWN
Platform: UNKNOWN
Classifier: Programming Language :: Python :: 3
Classifier: License :: OSI Approved :: MIT License
Classifier: Operating System :: OS Independent
Requires-Dist: python-dateutil
